tesgds/__init__.py
tesgds/channel.py
dhea_dheo-0.0.2.dist-info/LICENSE
dhea_dheo-0.0.2.dist-info/METADATA
dhea_dheo-0.0.2.dist-info/WHEEL
dhea_dheo-0.0.2.dist-info/top_level.txt
dhea_dheo-0.0.2.dist-info/RECORD
